ketitestlib/__init__.cpython-36m-x86_64-linux-gnu.so
ketitestlib/__init__.pyi
ketitestlib/classa.cpython-36m-x86_64-linux-gnu.so
ketitestlib/classa.pyi
ketitestlib/classb.cpython-36m-x86_64-linux-gnu.so
ketitestlib/classb.pyi
ketitestlib/modules/__init__.cpython-36m-x86_64-linux-gnu.so
ketitestlib/modules/__init__.pyi
ketitestlib/modules/classc.cpython-36m-x86_64-linux-gnu.so
ketitestlib/modules/classc.pyi
ketitestlib/modules/classd.cpython-36m-x86_64-linux-gnu.so
ketitestlib/modules/classd.pyi
ketitestlib-1.0.2.dist-info/LICENSE
ketitestlib-1.0.2.dist-info/METADATA
ketitestlib-1.0.2.dist-info/WHEEL
ketitestlib-1.0.2.dist-info/top_level.txt
ketitestlib-1.0.2.dist-info/RECORD
