Metadata-Version: 2.1
Name: ketitestlib
Version: 1.0.2
Summary: A Testing Library
Home-page: https://github.com/mtbui2010
Author: Trung M. Bui
Author-email: bmtrungvp@gmail.com
License: MIT
Keywords: AI,LIBRARY
Platform: UNKNOWN
Classifier: Programming Language :: Python :: 3
Classifier: License :: OSI Approved :: MIT License
Classifier: Operating System :: OS Independent
Requires-Python: >=3.6
Requires-Dist: numpy
